copcon/__init__.py
copcon/cli.py
copcon/exceptions.py
copcon/messages.py
copcon/core/.copconignore
copcon/core/__init__.py
copcon/core/autodiscover.py
copcon/core/clipboard.py
copcon/core/file_filter.py
copcon/core/file_reader.py
copcon/core/file_tree.py
copcon/core/report.py
copcon/utils/__init__.py
copcon/utils/logger.py
copcon-0.3.14.dist-info/METADATA
copcon-0.3.14.dist-info/WHEEL
copcon-0.3.14.dist-info/entry_points.txt
copcon-0.3.14.dist-info/licenses/LICENSE
copcon-0.3.14.dist-info/RECORD
