Metadata-Version: 2.4
Name: copcon
Version: 0.3.14
Author-email: Kasper Junge <kasperjuunge@gmail.com>
License-File: LICENSE
Requires-Python: <4.0,>=3.11
Requires-Dist: pathspec<1.0.0,>=0.12.1
Requires-Dist: pyperclip<2.0.0,>=1.8.2
Requires-Dist: pywin32<309,>=308; platform_system == 'Windows'
Requires-Dist: tiktoken>=0.8.0
Requires-Dist: typer<1.0.0,>=0.12.3
